aio_amqp/__init__.py
aio_amqp/client.py
aio_amqp/constants.py
aio_amqp/exceptions.py
aio_amqp/utils.py
aio_amqp/version.py
aio_amqp-0.1.1.dist-info/METADATA
aio_amqp-0.1.1.dist-info/WHEEL
aio_amqp-0.1.1.dist-info/top_level.txt
aio_amqp-0.1.1.dist-info/RECORD
