Metadata-Version: 2.1
Name: aio-amqp
Version: 0.1.1
Summary: Asynchronous AMQP client for 0.9.1 protocol version.
Home-page: https://github.com/NotJustAToy/aio-amqp
Author: Not Just A Toy Corp.
Author-email: dev@notjustatoy.com
License: Apache License 2.0
Keywords: amqp rabbitmq asyncio
Platform: UNKNOWN
Classifier: Development Status :: 4 - Beta
Classifier: Intended Audience :: Developers
Classifier: License :: OSI Approved :: Apache Software License
Classifier: Operating System :: MacOS :: MacOS X
Classifier: Operating System :: Microsoft :: Windows
Classifier: Operating System :: POSIX
Classifier: Natural Language :: English
Classifier: Programming Language :: Python
Classifier: Programming Language :: Python :: 3
Classifier: Programming Language :: Python :: 3.6
Classifier: Programming Language :: Python :: 3.7
Classifier: Programming Language :: Python :: 3.8
Classifier: Topic :: Communications
Classifier: Topic :: Internet
Requires-Python: >=3.6.0
Requires-Dist: pamqp (==2.3.0)
